thonny_edulint-0.7.4.dist-info/licenses/LICENSE
thonnycontrib/edulint/__init__.py
thonnycontrib/edulint/announcement_dialog.py
thonnycontrib/edulint/broom-green.png
thonnycontrib/edulint/feedback_dialog.py
thonnycontrib/edulint/pypi_helper.py
thonnycontrib/edulint/reporting.py
thonnycontrib/edulint/update_dialog.py
thonnycontrib/edulint/utils.py
thonnycontrib/edulint/version_checker.py
thonnycontrib/edulint/view.py
thonny_edulint-0.7.4.dist-info/METADATA
thonny_edulint-0.7.4.dist-info/WHEEL
thonny_edulint-0.7.4.dist-info/top_level.txt
thonny_edulint-0.7.4.dist-info/RECORD
