Metadata-Version: 2.4
Name: thonny-edulint
Version: 0.7.4
Summary: A plugin that adds EduLint warnings to the Thonny Python IDE.
Home-page: https://github.com/GiraffeReversed/thonny-edulint
Author: Anna Rechtackova
Author-email: anna.rechtackova@mail.muni.cz
License: GPLv3
Project-URL: Bug Tracker, https://github.com/GiraffeReversed/thonny-edulint/issues
Classifier: Programming Language :: Python :: 3
Classifier: Environment :: Plugins
Classifier: Intended Audience :: Education
Classifier: License :: OSI Approved :: GNU General Public License v3 (GPLv3)
Classifier: Operating System :: OS Independent
Requires-Python: >=3.8
License-File: LICENSE
Requires-Dist: thonny~=4.0
Requires-Dist: edulint~=4.0
Requires-Dist: mistune~=3.0
Requires-Dist: requests
Requires-Dist: platformdirs
Dynamic: author
Dynamic: author-email
Dynamic: classifier
Dynamic: description
Dynamic: description-content-type
Dynamic: home-page
Dynamic: license
Dynamic: license-file
Dynamic: project-url
Dynamic: requires-dist
Dynamic: requires-python
Dynamic: summary
